django_currency_updater/__init__.py
django_currency_updater/admin.py
django_currency_updater/apps.py
django_currency_updater/middleware.py
django_currency_updater/models.py
django_currency_updater/scheduler.py
django_currency_updater/settings.py
django_currency_updater/updater.py
django_currency_updater/urls.py
django_currency_updater/utils.py
django_currency_updater/views.py
django_currency_updater/management/__init__.py
django_currency_updater/management/commands/__init__.py
django_currency_updater/management/commands/load_currencies.py
django_currency_updater/management/commands/script.py
django_currency_updater/templatetags/__init__.py
django_currency_updater/templatetags/currency_tags.py
tests/__init__.py
tests/test_updater.py
django_currency_updater-0.1.0.dist-info/LICENSE
django_currency_updater-0.1.0.dist-info/METADATA
django_currency_updater-0.1.0.dist-info/WHEEL
django_currency_updater-0.1.0.dist-info/top_level.txt
django_currency_updater-0.1.0.dist-info/RECORD
