Metadata-Version: 2.1
Name: django-currency-updater
Version: 0.1.0
Summary: A reusable Django library for updating currency rates
Home-page: https://github.com/medaminerjb/django-currency-update
Author: medaminerjb
Author-email: meda30449@gmail.com
Classifier: Framework :: Django
Classifier: Programming Language :: Python :: 3
Classifier: License :: OSI Approved :: MIT License
Classifier: Operating System :: OS Independent
Requires-Python: >=3.6
License-File: LICENSE
Requires-Dist: Django>=3.2
Requires-Dist: requests
Provides-Extra: automation
Requires-Dist: apscheduler; extra == "automation"
